{
  "nodeName": "body",
  "children": [
    {
      "inSlot": false,
      "inShadow": false,
      "nodeName": "user-card",
      "id": "",
      "classList": [],
      "ownIndex": 0,
      "children": [{
        "inSlot": false,
        "inShadow": true,
        "nodeName": "div",
        "id": "",
        "classList": [],
        "ownIndex": 0,
        "children": [{
          "inSlot": false,
          "inShadow": false,
          "nodeName": "slot",
          "id": "",
          "classList": [],
          "name": "username",
          "ownIndex": 0,
          "children": [{
            "inSlot": true,
            "inShadow": false,
            "nodeName": "span",
            "id": "",
            "classList": [],
            "ownIndex": 0,
            "children": [],
            "_ref": "[0].children.[0].children.[0].children.[0]",
            "_selector": "body>user-card:nth-child(1)>::shadowroot>div:nth-child(1)>slot:nth-child(1)>span:nth-child(1)"
          }, {
            "inSlot": true,
            "inShadow": false,
            "nodeName": "div",
            "id": "",
            "classList": [],
            "ownIndex": 1,
            "children": [],
            "_ref": "[0].children.[0].children.[0].children.[1]",
            "_selector": "body>user-card:nth-child(1)>::shadowroot>div:nth-child(1)>slot:nth-child(1)>div:nth-child(2)"
          }],
          "_ref": "[0].children.[0].children.[0]",
          "_selector": "body>user-card:nth-child(1)>::shadowroot>div:nth-child(1)>slot:nth-child(1)"
        }],
        "_ref": "[0].children.[0]",
        "_selector": "body>user-card:nth-child(1)>::shadowroot>div:nth-child(1)"
      }, {
        "inSlot": false,
        "inShadow": true,
        "nodeName": "div",
        "id": "",
        "classList": [],
        "ownIndex": 1,
        "children": [{
          "inSlot": false,
          "inShadow": false,
          "nodeName": "slot",
          "id": "",
          "classList": [],
          "name": "birthday",
          "ownIndex": 0,
          "children": [{
            "inSlot": true,
            "inShadow": false,
            "nodeName": "span",
            "id": "",
            "classList": [],
            "ownIndex": 2,
            "children": [],
            "_ref": "[0].children.[1].children.[0].children.[0]",
            "_selector": "body>user-card:nth-child(1)>::shadowroot>div:nth-child(2)>slot:nth-child(1)>span:nth-child(3)"
          }],
          "_ref": "[0].children.[1].children.[0]",
          "_selector": "body>user-card:nth-child(1)>::shadowroot>div:nth-child(2)>slot:nth-child(1)"
        }],
        "_ref": "[0].children.[1]",
        "_selector": "body>user-card:nth-child(1)>::shadowroot>div:nth-child(2)"
      }],
      "_ref": "[0]",
      "_selector": "body>user-card:nth-child(1)"
    },
    {
      "inSlot": false,
      "inShadow": false,
      "nodeName": "div",
      "id": "container",
      "classList": [],
      "ownIndex": 1,
      "children": [{
        "inSlot": false,
        "inShadow": false,
        "nodeName": "div",
        "id": "",
        "classList": ["app"],
        "ownIndex": 0,
        "children": [{
          "inSlot": false,
          "inShadow": false,
          "nodeName": "div",
          "id": "",
          "classList": ["header"],
          "ownIndex": 0,
          "children": [{
            "inSlot": false,
            "inShadow": false,
            "nodeName": "div",
            "id": "",
            "classList": ["logo"],
            "ownIndex": 0,
            "children": [],
            "_ref": "[1].children.[0].children.[0].children.[0]",
            "_selector": "body>div:nth-child(2)>div:nth-child(1)>div:nth-child(1)>div:nth-child(1)"
          }, {
            "inSlot": false,
            "inShadow": false,
            "nodeName": "span",
            "id": "",
            "classList": ["message-container"],
            "ownIndex": 1,
            "children": [{
              "inSlot": false,
              "inShadow": false,
              "nodeName": "span",
              "id": "",
              "classList": ["message"],
              "ownIndex": 0,
              "children": [{
                "inSlot": false,
                "inShadow": false,
                "nodeName": "span",
                "id": "",
                "classList": ["text"],
                "ownIndex": 0,
                "children": [],
                "_ref": "[1].children.[0].children.[0].children.[1].children.[0].children.[0]",
                "_selector": "body>div:nth-child(2)>div:nth-child(1)>div:nth-child(1)>span:nth-child(2)>span:nth-child(1)>span:nth-child(1)"
              }],
              "_ref": "[1].children.[0].children.[0].children.[1].children.[0]",
              "_selector": "body>div:nth-child(2)>div:nth-child(1)>div:nth-child(1)>span:nth-child(2)>span:nth-child(1)"
            }],
            "_ref": "[1].children.[0].children.[0].children.[1]",
            "_selector": "body>div:nth-child(2)>div:nth-child(1)>div:nth-child(1)>span:nth-child(2)"
          }, {
            "inSlot": false,
            "inShadow": false,
            "nodeName": "div",
            "id": "",
            "classList": ["actions"],
            "ownIndex": 2,
            "children": [{
              "inSlot": false,
              "inShadow": false,
              "nodeName": "div",
              "id": "",
              "classList": ["ui-group"],
              "ownIndex": 0,
              "children": [{
                "inSlot": false,
                "inShadow": false,
                "nodeName": "div",
                "id": "",
                "classList": ["content-wrapper"],
                "ownIndex": 0,
                "children": [{
                  "inSlot": false,
                  "inShadow": false,
                  "nodeName": "div",
                  "id": "",
                  "classList": ["content"],
                  "ownIndex": 0,
                  "children": [{
                    "inSlot": false,
                    "inShadow": false,
                    "nodeName": "button",
                    "id": "",
                    "classList": [],
                    "name": "",
                    "ownIndex": 0,
                    "children": [],
                    "_ref": "[1].children.[0].children.[0].children.[2].children.[0].children.[0].children.[0].children.[0]",
                    "_selector": "body>div:nth-child(2)>div:nth-child(1)>div:nth-child(1)>div:nth-child(3)>div:nth-child(1)>div:nth-child(1)>div:nth-child(1)>button:nth-child(1)"
                  }, {
                    "inSlot": false,
                    "inShadow": false,
                    "nodeName": "button",
                    "id": "",
                    "classList": [],
                    "name": "",
                    "ownIndex": 1,
                    "children": [],
                    "_ref": "[1].children.[0].children.[0].children.[2].children.[0].children.[0].children.[0].children.[1]",
                    "_selector": "body>div:nth-child(2)>div:nth-child(1)>div:nth-child(1)>div:nth-child(3)>div:nth-child(1)>div:nth-child(1)>div:nth-child(1)>button:nth-child(2)"
                  }, {
                    "inSlot": false,
                    "inShadow": false,
                    "nodeName": "button",
                    "id": "",
                    "classList": [],
                    "name": "",
                    "ownIndex": 2,
                    "children": [],
                    "_ref": "[1].children.[0].children.[0].children.[2].children.[0].children.[0].children.[0].children.[2]",
                    "_selector": "body>div:nth-child(2)>div:nth-child(1)>div:nth-child(1)>div:nth-child(3)>div:nth-child(1)>div:nth-child(1)>div:nth-child(1)>button:nth-child(3)"
                  }, {
                    "inSlot": false,
                    "inShadow": false,
                    "nodeName": "button",
                    "id": "",
                    "classList": [],
                    "name": "",
                    "ownIndex": 3,
                    "children": [],
                    "_ref": "[1].children.[0].children.[0].children.[2].children.[0].children.[0].children.[0].children.[3]",
                    "_selector": "body>div:nth-child(2)>div:nth-child(1)>div:nth-child(1)>div:nth-child(3)>div:nth-child(1)>div:nth-child(1)>div:nth-child(1)>button:nth-child(4)"
                  }, {
                    "inSlot": false,
                    "inShadow": false,
                    "nodeName": "button",
                    "id": "",
                    "classList": [],
                    "name": "",
                    "ownIndex": 4,
                    "children": [],
                    "_ref": "[1].children.[0].children.[0].children.[2].children.[0].children.[0].children.[0].children.[4]",
                    "_selector": "body>div:nth-child(2)>div:nth-child(1)>div:nth-child(1)>div:nth-child(3)>div:nth-child(1)>div:nth-child(1)>div:nth-child(1)>button:nth-child(5)"
                  }],
                  "_ref": "[1].children.[0].children.[0].children.[2].children.[0].children.[0].children.[0]",
                  "_selector": "body>div:nth-child(2)>div:nth-child(1)>div:nth-child(1)>div:nth-child(3)>div:nth-child(1)>div:nth-child(1)>div:nth-child(1)"
                }],
                "_ref": "[1].children.[0].children.[0].children.[2].children.[0].children.[0]",
                "_selector": "body>div:nth-child(2)>div:nth-child(1)>div:nth-child(1)>div:nth-child(3)>div:nth-child(1)>div:nth-child(1)"
              }],
              "_ref": "[1].children.[0].children.[0].children.[2].children.[0]",
              "_selector": "body>div:nth-child(2)>div:nth-child(1)>div:nth-child(1)>div:nth-child(3)>div:nth-child(1)"
            }],
            "_ref": "[1].children.[0].children.[0].children.[2]",
            "_selector": "body>div:nth-child(2)>div:nth-child(1)>div:nth-child(1)>div:nth-child(3)"
          }],
          "_ref": "[1].children.[0].children.[0]",
          "_selector": "body>div:nth-child(2)>div:nth-child(1)>div:nth-child(1)"
        }, {
          "inSlot": false,
          "inShadow": false,
          "nodeName": "div",
          "id": "",
          "classList": ["container"],
          "ownIndex": 1,
          "children": [{
            "inSlot": false,
            "inShadow": false,
            "nodeName": "div",
            "id": "",
            "classList": ["split-pane", "vertical"],
            "ownIndex": 0,
            "children": [{
              "inSlot": false,
              "inShadow": false,
              "nodeName": "div",
              "id": "",
              "classList": ["left", "top"],
              "ownIndex": 0,
              "children": [{
                "inSlot": false,
                "inShadow": false,
                "nodeName": "div",
                "id": "",
                "classList": ["scroll-pane"],
                "ownIndex": 0,
                "children": [{
                  "inSlot": false,
                  "inShadow": false,
                  "nodeName": "div",
                  "id": "",
                  "classList": ["header"],
                  "ownIndex": 0,
                  "children": [{
                    "inSlot": false,
                    "inShadow": false,
                    "nodeName": "div",
                    "id": "",
                    "classList": ["action-header"],
                    "ownIndex": 0,
                    "children": [{
                      "inSlot": false,
                      "inShadow": false,
                      "nodeName": "input",
                      "id": "",
                      "classList": ["search"],
                      "name": "",
                      "ownIndex": 0,
                      "children": [],
                      "_ref": "[1].children.[0].children.[1].children.[0].children.[0].children.[0].children.[0].children.[0].children.[0]",
                      "_selector": "body>div:nth-child(2)>div:nth-child(1)>div:nth-child(2)>div:nth-child(1)>div:nth-child(1)>div:nth-child(1)>div:nth-child(1)>div:nth-child(1)>input:nth-child(1)"
                    }],
                    "_ref": "[1].children.[0].children.[1].children.[0].children.[0].children.[0].children.[0].children.[0]",
                    "_selector": "body>div:nth-child(2)>div:nth-child(1)>div:nth-child(2)>div:nth-child(1)>div:nth-child(1)>div:nth-child(1)>div:nth-child(1)>div:nth-child(1)"
                  }],
                  "_ref": "[1].children.[0].children.[1].children.[0].children.[0].children.[0].children.[0]",
                  "_selector": "body>div:nth-child(2)>div:nth-child(1)>div:nth-child(2)>div:nth-child(1)>div:nth-child(1)>div:nth-child(1)>div:nth-child(1)"
                }, {
                  "inSlot": false,
                  "inShadow": false,
                  "nodeName": "div",
                  "id": "",
                  "classList": ["scroll"],
                  "ownIndex": 1,
                  "children": [{
                    "inSlot": false,
                    "inShadow": false,
                    "nodeName": "div",
                    "id": "",
                    "classList": ["tree"],
                    "ownIndex": 0,
                    "children": [{
                      "inSlot": false,
                      "inShadow": false,
                      "nodeName": "ul",
                      "id": "myUL",
                      "classList": [],
                      "ownIndex": 0,
                      "children": [{
                        "inSlot": false,
                        "inShadow": false,
                        "nodeName": "li",
                        "id": "",
                        "classList": [],
                        "ownIndex": 0,
                        "children": [{
                          "inSlot": false,
                          "inShadow": false,
                          "nodeName": "span",
                          "id": "",
                          "classList": ["caret"],
                          "ownIndex": 0,
                          "children": [],
                          "_ref": "[1].children.[0].children.[1].children.[0].children.[0].children.[0].children.[1].children.[0].children.[0].children.[0].children.[0]",
                          "_selector": "body>div:nth-child(2)>div:nth-child(1)>div:nth-child(2)>div:nth-child(1)>div:nth-child(1)>div:nth-child(1)>div:nth-child(2)>div:nth-child(1)>ul:nth-child(1)>li:nth-child(1)>span:nth-child(1)"
                        }, {
                          "inSlot": false,
                          "inShadow": false,
                          "nodeName": "ul",
                          "id": "",
                          "classList": ["active"],
                          "ownIndex": 1,
                          "children": [{
                            "inSlot": false,
                            "inShadow": false,
                            "nodeName": "li",
                            "id": "",
                            "classList": [],
                            "ownIndex": 0,
                            "children": [],
                            "_ref": "[1].children.[0].children.[1].children.[0].children.[0].children.[0].children.[1].children.[0].children.[0].children.[0].children.[1].children.[0]",
                            "_selector": "body>div:nth-child(2)>div:nth-child(1)>div:nth-child(2)>div:nth-child(1)>div:nth-child(1)>div:nth-child(1)>div:nth-child(2)>div:nth-child(1)>ul:nth-child(1)>li:nth-child(1)>ul:nth-child(2)>li:nth-child(1)"
                          }, {
                            "inSlot": false,
                            "inShadow": false,
                            "nodeName": "li",
                            "id": "",
                            "classList": [],
                            "ownIndex": 1,
                            "children": [],
                            "_ref": "[1].children.[0].children.[1].children.[0].children.[0].children.[0].children.[1].children.[0].children.[0].children.[0].children.[1].children.[1]",
                            "_selector": "body>div:nth-child(2)>div:nth-child(1)>div:nth-child(2)>div:nth-child(1)>div:nth-child(1)>div:nth-child(1)>div:nth-child(2)>div:nth-child(1)>ul:nth-child(1)>li:nth-child(1)>ul:nth-child(2)>li:nth-child(2)"
                          }, {
                            "inSlot": false,
                            "inShadow": false,
                            "nodeName": "li",
                            "id": "",
                            "classList": [],
                            "ownIndex": 2,
                            "children": [{
                              "inSlot": false,
                              "inShadow": false,
                              "nodeName": "span",
                              "id": "",
                              "classList": ["caret"],
                              "ownIndex": 0,
                              "children": [],
                              "_ref": "[1].children.[0].children.[1].children.[0].children.[0].children.[0].children.[1].children.[0].children.[0].children.[0].children.[1].children.[2].children.[0]",
                              "_selector": "body>div:nth-child(2)>div:nth-child(1)>div:nth-child(2)>div:nth-child(1)>div:nth-child(1)>div:nth-child(1)>div:nth-child(2)>div:nth-child(1)>ul:nth-child(1)>li:nth-child(1)>ul:nth-child(2)>li:nth-child(3)>span:nth-child(1)"
                            }, {
                              "inSlot": false,
                              "inShadow": false,
                              "nodeName": "ul",
                              "id": "",
                              "classList": ["active"],
                              "ownIndex": 1,
                              "children": [{
                                "inSlot": false,
                                "inShadow": false,
                                "nodeName": "li",
                                "id": "",
                                "classList": [],
                                "ownIndex": 0,
                                "children": [],
                                "_ref": "[1].children.[0].children.[1].children.[0].children.[0].children.[0].children.[1].children.[0].children.[0].children.[0].children.[1].children.[2].children.[1].children.[0]",
                                "_selector": "body>div:nth-child(2)>div:nth-child(1)>div:nth-child(2)>div:nth-child(1)>div:nth-child(1)>div:nth-child(1)>div:nth-child(2)>div:nth-child(1)>ul:nth-child(1)>li:nth-child(1)>ul:nth-child(2)>li:nth-child(3)>ul:nth-child(2)>li:nth-child(1)"
                              }, {
                                "inSlot": false,
                                "inShadow": false,
                                "nodeName": "li",
                                "id": "",
                                "classList": [],
                                "ownIndex": 1,
                                "children": [],
                                "_ref": "[1].children.[0].children.[1].children.[0].children.[0].children.[0].children.[1].children.[0].children.[0].children.[0].children.[1].children.[2].children.[1].children.[1]",
                                "_selector": "body>div:nth-child(2)>div:nth-child(1)>div:nth-child(2)>div:nth-child(1)>div:nth-child(1)>div:nth-child(1)>div:nth-child(2)>div:nth-child(1)>ul:nth-child(1)>li:nth-child(1)>ul:nth-child(2)>li:nth-child(3)>ul:nth-child(2)>li:nth-child(2)"
                              }, {
                                "inSlot": false,
                                "inShadow": false,
                                "nodeName": "li",
                                "id": "",
                                "classList": [],
                                "ownIndex": 2,
                                "children": [{
                                  "inSlot": false,
                                  "inShadow": false,
                                  "nodeName": "span",
                                  "id": "",
                                  "classList": ["caret"],
                                  "ownIndex": 0,
                                  "children": [],
                                  "_ref": "[1].children.[0].children.[1].children.[0].children.[0].children.[0].children.[1].children.[0].children.[0].children.[0].children.[1].children.[2].children.[1].children.[2].children.[0]",
                                  "_selector": "body>div:nth-child(2)>div:nth-child(1)>div:nth-child(2)>div:nth-child(1)>div:nth-child(1)>div:nth-child(1)>div:nth-child(2)>div:nth-child(1)>ul:nth-child(1)>li:nth-child(1)>ul:nth-child(2)>li:nth-child(3)>ul:nth-child(2)>li:nth-child(3)>span:nth-child(1)"
                                }, {
                                  "inSlot": false,
                                  "inShadow": false,
                                  "nodeName": "ul",
                                  "id": "",
                                  "classList": ["active"],
                                  "ownIndex": 1,
                                  "children": [{
                                    "inSlot": false,
                                    "inShadow": false,
                                    "nodeName": "li",
                                    "id": "",
                                    "classList": [],
                                    "ownIndex": 0,
                                    "children": [],
                                    "_ref": "[1].children.[0].children.[1].children.[0].children.[0].children.[0].children.[1].children.[0].children.[0].children.[0].children.[1].children.[2].children.[1].children.[2].children.[1].children.[0]",
                                    "_selector": "body>div:nth-child(2)>div:nth-child(1)>div:nth-child(2)>div:nth-child(1)>div:nth-child(1)>div:nth-child(1)>div:nth-child(2)>div:nth-child(1)>ul:nth-child(1)>li:nth-child(1)>ul:nth-child(2)>li:nth-child(3)>ul:nth-child(2)>li:nth-child(3)>ul:nth-child(2)>li:nth-child(1)"
                                  }, {
                                    "inSlot": false,
                                    "inShadow": false,
                                    "nodeName": "li",
                                    "id": "",
                                    "classList": [],
                                    "ownIndex": 1,
                                    "children": [],
                                    "_ref": "[1].children.[0].children.[1].children.[0].children.[0].children.[0].children.[1].children.[0].children.[0].children.[0].children.[1].children.[2].children.[1].children.[2].children.[1].children.[1]",
                                    "_selector": "body>div:nth-child(2)>div:nth-child(1)>div:nth-child(2)>div:nth-child(1)>div:nth-child(1)>div:nth-child(1)>div:nth-child(2)>div:nth-child(1)>ul:nth-child(1)>li:nth-child(1)>ul:nth-child(2)>li:nth-child(3)>ul:nth-child(2)>li:nth-child(3)>ul:nth-child(2)>li:nth-child(2)"
                                  }, {
                                    "inSlot": false,
                                    "inShadow": false,
                                    "nodeName": "li",
                                    "id": "",
                                    "classList": [],
                                    "ownIndex": 2,
                                    "children": [],
                                    "_ref": "[1].children.[0].children.[1].children.[0].children.[0].children.[0].children.[1].children.[0].children.[0].children.[0].children.[1].children.[2].children.[1].children.[2].children.[1].children.[2]",
                                    "_selector": "body>div:nth-child(2)>div:nth-child(1)>div:nth-child(2)>div:nth-child(1)>div:nth-child(1)>div:nth-child(1)>div:nth-child(2)>div:nth-child(1)>ul:nth-child(1)>li:nth-child(1)>ul:nth-child(2)>li:nth-child(3)>ul:nth-child(2)>li:nth-child(3)>ul:nth-child(2)>li:nth-child(3)"
                                  }, {
                                    "inSlot": false,
                                    "inShadow": false,
                                    "nodeName": "li",
                                    "id": "",
                                    "classList": [],
                                    "ownIndex": 3,
                                    "children": [],
                                    "_ref": "[1].children.[0].children.[1].children.[0].children.[0].children.[0].children.[1].children.[0].children.[0].children.[0].children.[1].children.[2].children.[1].children.[2].children.[1].children.[3]",
                                    "_selector": "body>div:nth-child(2)>div:nth-child(1)>div:nth-child(2)>div:nth-child(1)>div:nth-child(1)>div:nth-child(1)>div:nth-child(2)>div:nth-child(1)>ul:nth-child(1)>li:nth-child(1)>ul:nth-child(2)>li:nth-child(3)>ul:nth-child(2)>li:nth-child(3)>ul:nth-child(2)>li:nth-child(4)"
                                  }],
                                  "_ref": "[1].children.[0].children.[1].children.[0].children.[0].children.[0].children.[1].children.[0].children.[0].children.[0].children.[1].children.[2].children.[1].children.[2].children.[1]",
                                  "_selector": "body>div:nth-child(2)>div:nth-child(1)>div:nth-child(2)>div:nth-child(1)>div:nth-child(1)>div:nth-child(1)>div:nth-child(2)>div:nth-child(1)>ul:nth-child(1)>li:nth-child(1)>ul:nth-child(2)>li:nth-child(3)>ul:nth-child(2)>li:nth-child(3)>ul:nth-child(2)"
                                }],
                                "_ref": "[1].children.[0].children.[1].children.[0].children.[0].children.[0].children.[1].children.[0].children.[0].children.[0].children.[1].children.[2].children.[1].children.[2]",
                                "_selector": "body>div:nth-child(2)>div:nth-child(1)>div:nth-child(2)>div:nth-child(1)>div:nth-child(1)>div:nth-child(1)>div:nth-child(2)>div:nth-child(1)>ul:nth-child(1)>li:nth-child(1)>ul:nth-child(2)>li:nth-child(3)>ul:nth-child(2)>li:nth-child(3)"
                              }],
                              "_ref": "[1].children.[0].children.[1].children.[0].children.[0].children.[0].children.[1].children.[0].children.[0].children.[0].children.[1].children.[2].children.[1]",
                              "_selector": "body>div:nth-child(2)>div:nth-child(1)>div:nth-child(2)>div:nth-child(1)>div:nth-child(1)>div:nth-child(1)>div:nth-child(2)>div:nth-child(1)>ul:nth-child(1)>li:nth-child(1)>ul:nth-child(2)>li:nth-child(3)>ul:nth-child(2)"
                            }],
                            "_ref": "[1].children.[0].children.[1].children.[0].children.[0].children.[0].children.[1].children.[0].children.[0].children.[0].children.[1].children.[2]",
                            "_selector": "body>div:nth-child(2)>div:nth-child(1)>div:nth-child(2)>div:nth-child(1)>div:nth-child(1)>div:nth-child(1)>div:nth-child(2)>div:nth-child(1)>ul:nth-child(1)>li:nth-child(1)>ul:nth-child(2)>li:nth-child(3)"
                          }],
                          "_ref": "[1].children.[0].children.[1].children.[0].children.[0].children.[0].children.[1].children.[0].children.[0].children.[0].children.[1]",
                          "_selector": "body>div:nth-child(2)>div:nth-child(1)>div:nth-child(2)>div:nth-child(1)>div:nth-child(1)>div:nth-child(1)>div:nth-child(2)>div:nth-child(1)>ul:nth-child(1)>li:nth-child(1)>ul:nth-child(2)"
                        }],
                        "_ref": "[1].children.[0].children.[1].children.[0].children.[0].children.[0].children.[1].children.[0].children.[0].children.[0]",
                        "_selector": "body>div:nth-child(2)>div:nth-child(1)>div:nth-child(2)>div:nth-child(1)>div:nth-child(1)>div:nth-child(1)>div:nth-child(2)>div:nth-child(1)>ul:nth-child(1)>li:nth-child(1)"
                      }],
                      "_ref": "[1].children.[0].children.[1].children.[0].children.[0].children.[0].children.[1].children.[0].children.[0]",
                      "_selector": "body>div:nth-child(2)>div:nth-child(1)>div:nth-child(2)>div:nth-child(1)>div:nth-child(1)>div:nth-child(1)>div:nth-child(2)>div:nth-child(1)>ul:nth-child(1)"
                    }],
                    "_ref": "[1].children.[0].children.[1].children.[0].children.[0].children.[0].children.[1].children.[0]",
                    "_selector": "body>div:nth-child(2)>div:nth-child(1)>div:nth-child(2)>div:nth-child(1)>div:nth-child(1)>div:nth-child(1)>div:nth-child(2)>div:nth-child(1)"
                  }],
                  "_ref": "[1].children.[0].children.[1].children.[0].children.[0].children.[0].children.[1]",
                  "_selector": "body>div:nth-child(2)>div:nth-child(1)>div:nth-child(2)>div:nth-child(1)>div:nth-child(1)>div:nth-child(1)>div:nth-child(2)"
                }],
                "_ref": "[1].children.[0].children.[1].children.[0].children.[0].children.[0]",
                "_selector": "body>div:nth-child(2)>div:nth-child(1)>div:nth-child(2)>div:nth-child(1)>div:nth-child(1)>div:nth-child(1)"
              }, {
                "inSlot": false,
                "inShadow": false,
                "nodeName": "div",
                "id": "",
                "classList": ["dragger"],
                "ownIndex": 1,
                "children": [],
                "_ref": "[1].children.[0].children.[1].children.[0].children.[0].children.[1]",
                "_selector": "body>div:nth-child(2)>div:nth-child(1)>div:nth-child(2)>div:nth-child(1)>div:nth-child(1)>div:nth-child(2)"
              }],
              "_ref": "[1].children.[0].children.[1].children.[0].children.[0]",
              "_selector": "body>div:nth-child(2)>div:nth-child(1)>div:nth-child(2)>div:nth-child(1)>div:nth-child(1)"
            }, {
              "inSlot": false,
              "inShadow": false,
              "nodeName": "div",
              "id": "",
              "classList": ["right", "bottom"],
              "ownIndex": 1,
              "children": [{
                "inSlot": false,
                "inShadow": false,
                "nodeName": "div",
                "id": "",
                "classList": ["scroll-pane"],
                "ownIndex": 0,
                "children": [{
                  "inSlot": false,
                  "inShadow": false,
                  "nodeName": "div",
                  "id": "",
                  "classList": ["header"],
                  "ownIndex": 0,
                  "children": [{
                    "inSlot": false,
                    "inShadow": false,
                    "nodeName": "div",
                    "id": "",
                    "classList": ["action-header"],
                    "ownIndex": 0,
                    "children": [{
                      "inSlot": false,
                      "inShadow": false,
                      "nodeName": "span",
                      "id": "",
                      "classList": ["title"],
                      "ownIndex": 0,
                      "children": [],
                      "_ref": "[1].children.[0].children.[1].children.[0].children.[1].children.[0].children.[0].children.[0].children.[0]",
                      "_selector": "body>div:nth-child(2)>div:nth-child(1)>div:nth-child(2)>div:nth-child(1)>div:nth-child(2)>div:nth-child(1)>div:nth-child(1)>div:nth-child(1)>span:nth-child(1)"
                    }, {
                      "inSlot": false,
                      "inShadow": false,
                      "nodeName": "input",
                      "id": "",
                      "classList": ["search"],
                      "name": "",
                      "ownIndex": 1,
                      "children": [],
                      "_ref": "[1].children.[0].children.[1].children.[0].children.[1].children.[0].children.[0].children.[0].children.[1]",
                      "_selector": "body>div:nth-child(2)>div:nth-child(1)>div:nth-child(2)>div:nth-child(1)>div:nth-child(2)>div:nth-child(1)>div:nth-child(1)>div:nth-child(1)>input:nth-child(2)"
                    }],
                    "_ref": "[1].children.[0].children.[1].children.[0].children.[1].children.[0].children.[0].children.[0]",
                    "_selector": "body>div:nth-child(2)>div:nth-child(1)>div:nth-child(2)>div:nth-child(1)>div:nth-child(2)>div:nth-child(1)>div:nth-child(1)>div:nth-child(1)"
                  }],
                  "_ref": "[1].children.[0].children.[1].children.[0].children.[1].children.[0].children.[0]",
                  "_selector": "body>div:nth-child(2)>div:nth-child(1)>div:nth-child(2)>div:nth-child(1)>div:nth-child(2)>div:nth-child(1)>div:nth-child(1)"
                }, {
                  "inSlot": false,
                  "inShadow": false,
                  "nodeName": "div",
                  "id": "",
                  "classList": ["scroll"],
                  "ownIndex": 1,
                  "children": [{
                    "inSlot": false,
                    "inShadow": false,
                    "nodeName": "section",
                    "id": "",
                    "classList": ["notice"],
                    "ownIndex": 0,
                    "children": [{
                      "inSlot": false,
                      "inShadow": false,
                      "nodeName": "div",
                      "id": "",
                      "classList": [],
                      "ownIndex": 0,
                      "children": [],
                      "_ref": "[1].children.[0].children.[1].children.[0].children.[1].children.[0].children.[1].children.[0].children.[0]",
                      "_selector": "body>div:nth-child(2)>div:nth-child(1)>div:nth-child(2)>div:nth-child(1)>div:nth-child(2)>div:nth-child(1)>div:nth-child(2)>section:nth-child(1)>div:nth-child(1)"
                    }],
                    "_ref": "[1].children.[0].children.[1].children.[0].children.[1].children.[0].children.[1].children.[0]",
                    "_selector": "body>div:nth-child(2)>div:nth-child(1)>div:nth-child(2)>div:nth-child(1)>div:nth-child(2)>div:nth-child(1)>div:nth-child(2)>section:nth-child(1)"
                  }],
                  "_ref": "[1].children.[0].children.[1].children.[0].children.[1].children.[0].children.[1]",
                  "_selector": "body>div:nth-child(2)>div:nth-child(1)>div:nth-child(2)>div:nth-child(1)>div:nth-child(2)>div:nth-child(1)>div:nth-child(2)"
                }],
                "_ref": "[1].children.[0].children.[1].children.[0].children.[1].children.[0]",
                "_selector": "body>div:nth-child(2)>div:nth-child(1)>div:nth-child(2)>div:nth-child(1)>div:nth-child(2)>div:nth-child(1)"
              }],
              "_ref": "[1].children.[0].children.[1].children.[0].children.[1]",
              "_selector": "body>div:nth-child(2)>div:nth-child(1)>div:nth-child(2)>div:nth-child(1)>div:nth-child(2)"
            }],
            "_ref": "[1].children.[0].children.[1].children.[0]",
            "_selector": "body>div:nth-child(2)>div:nth-child(1)>div:nth-child(2)>div:nth-child(1)"
          }],
          "_ref": "[1].children.[0].children.[1]",
          "_selector": "body>div:nth-child(2)>div:nth-child(1)>div:nth-child(2)"
        }],
        "_ref": "[1].children.[0]",
        "_selector": "body>div:nth-child(2)>div:nth-child(1)"
      }],
      "_ref": "[1]",
      "_selector": "body>div:nth-child(2)"
    },
    {
      "inSlot": false,
      "inShadow": false,
      "nodeName": "div",
      "id": "app",
      "classList": [],
      "ownIndex": 2,
      "children": [{
        "inSlot": false,
        "inShadow": false,
        "nodeName": "p",
        "id": "",
        "classList": [],
        "ownIndex": 0,
        "children": [],
        "_ref": "[2].children.[0]",
        "_selector": "body>div:nth-child(3)>p:nth-child(1)"
      }],
      "_ref": "[2]",
      "_selector": "body>div:nth-child(3)"
    }
  ]
}
